odoo8_addon_crm_deduplicate_filter-8.0.1.0.0-py2.7-nspkg.pth
odoo_addons/crm_deduplicate_filter/__openerp__.py
odoo_addons/crm_deduplicate_filter/__init__.py
odoo_addons/crm_deduplicate_filter/README.rst
odoo_addons/crm_deduplicate_filter/i18n/es.po
odoo_addons/crm_deduplicate_filter/wizards/partner_merge.py
odoo_addons/crm_deduplicate_filter/wizards/__init__.py
odoo_addons/crm_deduplicate_filter/wizards/partner_merge_view.xml
odoo_addons/crm_deduplicate_filter/tests/__init__.py
odoo_addons/crm_deduplicate_filter/tests/test_crm_deduplicate_filter.py
odoo_addons/crm_deduplicate_filter/static/description/icon.svg
odoo_addons/crm_deduplicate_filter/static/description/icon.png
odoo8_addon_crm_deduplicate_filter-8.0.1.0.0.dist-info/top_level.txt
odoo8_addon_crm_deduplicate_filter-8.0.1.0.0.dist-info/WHEEL
odoo8_addon_crm_deduplicate_filter-8.0.1.0.0.dist-info/RECORD
odoo8_addon_crm_deduplicate_filter-8.0.1.0.0.dist-info/metadata.json
odoo8_addon_crm_deduplicate_filter-8.0.1.0.0.dist-info/DESCRIPTION.rst
odoo8_addon_crm_deduplicate_filter-8.0.1.0.0.dist-info/METADATA
odoo8_addon_crm_deduplicate_filter-8.0.1.0.0.dist-info/namespace_packages.txt
